{
  "annotations": {
    "list": []
  },
  "editable": true,
  "fiscalYearStartMonth": 0,
  "graphTooltip": 0,
  "id": null,
  "links": [],
  "panels": [
    {
      "datasource": {
        "type": "postgres",
        "uid": "steampipe"
      },
      "fieldConfig": {
        "defaults": {
          "color": {
            "mode": "thresholds"
          },
          "mappings": [],
          "thresholds": {
            "steps": [
              {
                "color": "blue",
                "value": null
              }
            ]
          },
          "unit": "short"
        },
        "overrides": []
      },
      "gridPos": {
        "h": 8,
        "w": 4,
        "x": 0,
        "y": 0
      },
      "id": 1,
      "options": {
        "colorMode": "value",
        "graphMode": "area",
        "justifyMode": "center",
        "orientation": "auto",
        "reduceOptions": {
          "calcs": [
            "lastNotNull"
          ],
          "fields": "",
          "values": false
        },
        "textMode": "value_and_name"
      },
      "pluginVersion": "12.3.3",
      "targets": [
        {
          "datasource": {
            "type": "postgres",
            "uid": "steampipe"
          },
          "format": "table",
          "rawQuery": true,
          "rawSql": "SELECT COUNT(*) as value FROM aws_ec2_instance",
          "refId": "A"
        }
      ],
      "title": "총 인스턴스",
      "type": "stat"
    },
    {
      "datasource": {
        "type": "postgres",
        "uid": "steampipe"
      },
      "fieldConfig": {
        "defaults": {
          "color": {
            "mode": "thresholds"
          },
          "mappings": [],
          "thresholds": {
            "steps": [
              {
                "color": "green",
                "value": null
              }
            ]
          },
          "unit": "short"
        },
        "overrides": []
      },
      "gridPos": {
        "h": 8,
        "w": 4,
        "x": 4,
        "y": 0
      },
      "id": 2,
      "options": {
        "colorMode": "value",
        "graphMode": "area",
        "justifyMode": "center",
        "orientation": "auto",
        "reduceOptions": {
          "calcs": [
            "lastNotNull"
          ],
          "fields": "",
          "values": false
        },
        "textMode": "value_and_name"
      },
      "pluginVersion": "12.3.3",
      "targets": [
        {
          "datasource": {
            "type": "postgres",
            "uid": "steampipe"
          },
          "format": "table",
          "rawQuery": true,
          "rawSql": "SELECT COUNT(*) as value FROM aws_ec2_instance WHERE instance_state = 'running'",
          "refId": "A"
        }
      ],
      "title": "🟢 실행중",
      "type": "stat"
    },
    {
      "datasource": {
        "type": "postgres",
        "uid": "steampipe"
      },
      "fieldConfig": {
        "defaults": {
          "color": {
            "mode": "thresholds"
          },
          "mappings": [],
          "thresholds": {
            "steps": [
              {
                "color": "red",
                "value": null
              }
            ]
          },
          "unit": "short"
        },
        "overrides": []
      },
      "gridPos": {
        "h": 8,
        "w": 4,
        "x": 8,
        "y": 0
      },
      "id": 3,
      "options": {
        "colorMode": "value",
        "graphMode": "area",
        "justifyMode": "center",
        "orientation": "auto",
        "reduceOptions": {
          "calcs": [
            "lastNotNull"
          ],
          "fields": "",
          "values": false
        },
        "textMode": "value_and_name"
      },
      "pluginVersion": "12.3.3",
      "targets": [
        {
          "datasource": {
            "type": "postgres",
            "uid": "steampipe"
          },
          "format": "table",
          "rawQuery": true,
          "rawSql": "SELECT COUNT(*) as value FROM aws_ec2_instance WHERE instance_state = 'stopped'",
          "refId": "A"
        }
      ],
      "title": "🔴 중지됨",
      "type": "stat"
    },
    {
      "datasource": {
        "type": "postgres",
        "uid": "steampipe"
      },
      "fieldConfig": {
        "defaults": {
          "custom": {
            "align": "auto",
            "cellOptions": {
              "type": "auto"
            },
            "inspect": false
          },
          "mappings": [],
          "thresholds": {
            "mode": "absolute",
            "steps": [
              {
                "color": "green",
                "value": null
              }
            ]
          }
        },
        "overrides": []
      },
      "gridPos": {
        "h": 8,
        "w": 12,
        "x": 12,
        "y": 0
      },
      "id": 4,
      "options": {
        "cellHeight": "sm",
        "footer": {
          "countRows": false,
          "fields": "",
          "reducer": [
            "sum"
          ],
          "show": false
        },
        "showHeader": true
      },
      "pluginVersion": "12.3.3",
      "targets": [
        {
          "datasource": {
            "type": "postgres",
            "uid": "steampipe"
          },
          "format": "table",
          "rawQuery": true,
          "rawSql": "SELECT \n  instance_state as \"상태\",\n  COUNT(*) as \"개수\",\n  ROUND(COUNT(*) * 100.0 / (SELECT COUNT(*) FROM aws_ec2_instance), 1) as \"비율(%)\"\nFROM aws_ec2_instance \nGROUP BY instance_state\nORDER BY COUNT(*) DESC",
          "refId": "A"
        }
      ],
      "title": "상태별 분포 (테이블)",
      "type": "table"
    },
    {
      "datasource": {
        "type": "postgres",
        "uid": "steampipe"
      },
      "fieldConfig": {
        "defaults": {
          "custom": {
            "align": "auto",
            "cellOptions": {
              "type": "auto"
            },
            "inspect": false
          },
          "mappings": [],
          "thresholds": {
            "mode": "absolute",
            "steps": [
              {
                "color": "green",
                "value": null
              }
            ]
          }
        },
        "overrides": []
      },
      "gridPos": {
        "h": 8,
        "w": 12,
        "x": 0,
        "y": 8
      },
      "id": 5,
      "options": {
        "cellHeight": "sm",
        "footer": {
          "countRows": false,
          "fields": "",
          "reducer": [
            "sum"
          ],
          "show": false
        },
        "showHeader": true
      },
      "pluginVersion": "12.3.3",
      "targets": [
        {
          "datasource": {
            "type": "postgres",
            "uid": "steampipe"
          },
          "format": "table",
          "rawQuery": true,
          "rawSql": "SELECT \n  instance_type as \"타입\",\n  COUNT(*) as \"개수\"\nFROM aws_ec2_instance \nGROUP BY instance_type\nORDER BY COUNT(*) DESC",
          "refId": "A"
        }
      ],
      "title": "타입별 분포 (테이블)",
      "type": "table"
    },
    {
      "datasource": {
        "type": "postgres",
        "uid": "steampipe"
      },
      "fieldConfig": {
        "defaults": {
          "custom": {
            "align": "auto",
            "cellOptions": {
              "type": "auto"
            },
            "inspect": false
          },
          "mappings": [],
          "thresholds": {
            "mode": "absolute",
            "steps": [
              {
                "color": "green",
                "value": null
              }
            ]
          }
        },
        "overrides": []
      },
      "gridPos": {
        "h": 8,
        "w": 12,
        "x": 12,
        "y": 8
      },
      "id": 6,
      "options": {
        "cellHeight": "sm",
        "footer": {
          "countRows": false,
          "fields": "",
          "reducer": [
            "sum"
          ],
          "show": false
        },
        "showHeader": true
      },
      "pluginVersion": "12.3.3",
      "targets": [
        {
          "datasource": {
            "type": "postgres",
            "uid": "steampipe"
          },
          "format": "table",
          "rawQuery": true,
          "rawSql": "SELECT \n  placement_availability_zone as \"가용성 영역\",\n  COUNT(*) as \"개수\"\nFROM aws_ec2_instance \nGROUP BY placement_availability_zone\nORDER BY COUNT(*) DESC",
          "refId": "A"
        }
      ],
      "title": "가용성 영역별 분포 (테이블)",
      "type": "table"
    },
    {
      "datasource": {
        "type": "postgres",
        "uid": "steampipe"
      },
      "fieldConfig": {
        "defaults": {
          "custom": {
            "align": "auto",
            "cellOptions": {
              "type": "auto"
            },
            "inspect": false
          },
          "mappings": [],
          "thresholds": {
            "mode": "absolute",
            "steps": [
              {
                "color": "green",
                "value": null
              }
            ]
          }
        },
        "overrides": []
      },
      "gridPos": {
        "h": 10,
        "w": 24,
        "x": 0,
        "y": 16
      },
      "id": 7,
      "options": {
        "cellHeight": "sm",
        "footer": {
          "countRows": false,
          "fields": "",
          "reducer": [
            "sum"
          ],
          "show": false
        },
        "showHeader": true
      },
      "pluginVersion": "12.3.3",
      "targets": [
        {
          "datasource": {
            "type": "postgres",
            "uid": "steampipe"
          },
          "format": "table",
          "rawQuery": true,
          "rawSql": "SELECT \n  instance_id as \"Instance ID\",\n  instance_type as \"타입\",\n  instance_state as \"상태\",\n  placement_availability_zone as \"가용성 영역\",\n  COALESCE(public_ip_address, 'None') as \"퍼블릭 IP\",\n  private_ip_address as \"프라이빗 IP\"\nFROM aws_ec2_instance \nORDER BY instance_state, instance_type",
          "refId": "A"
        }
      ],
      "title": "EC2 인스턴스 상세 정보",
      "type": "table"
    }
  ],
  "refresh": "30s",
  "schemaVersion": 39,
  "tags": [
    "aws",
    "ec2"
  ],
  "templating": {
    "list": []
  },
  "time": {
    "from": "now-6h",
    "to": "now"
  },
  "timepicker": {},
  "timezone": "browser",
  "title": "AWS EC2 모니터링 (안전 버전)",
  "uid": "ec2-safe-v12",
  "version": 1
}